z3c/formwidget/query/README.txt
z3c/formwidget/query/__init__.py
z3c/formwidget/query/configure.zcml
z3c/formwidget/query/i18n.sh
z3c/formwidget/query/interfaces.py
z3c/formwidget/query/tests.py
z3c/formwidget/query/widget.py
z3c/formwidget/query/locales/z3c.formwidget.query-manual.pot
z3c/formwidget/query/locales/z3c.formwidget.query.pot
z3c/formwidget/query/locales/en/LC_MESSAGES/z3c.formwidget.query.po
z3c/formwidget/query/locales/it/LC_MESSAGES/z3c.formwidget.query.po
z3c/formwidget/query/locales/nl/LC_MESSAGES/z3c.formwidget.query.po
z3c/formwidget/query/locales/zh_CN/LC_MESSAGES/z3c.formwidget.query.po
z3c_formwidget_query-3.0.dist-info/LICENSE.txt
z3c_formwidget_query-3.0.dist-info/METADATA
z3c_formwidget_query-3.0.dist-info/WHEEL
z3c_formwidget_query-3.0.dist-info/entry_points.txt
z3c_formwidget_query-3.0.dist-info/top_level.txt
z3c_formwidget_query-3.0.dist-info/RECORD
