Metadata-Version: 2.2
Name: z3c.formwidget.query
Version: 3.0
Summary: A source query widget for z3c.form.
Home-page: https://github.com/zopefoundation/z3c.formwidget.query
Author: Zope Community
Author-email: zope-dev@zope.dev
License: ZPL-2.1
Keywords: zope zope3 z3c.form
Classifier: Development Status :: 4 - Beta
Classifier: Environment :: Web Environment
Classifier: Framework :: Zope :: 3
Classifier: Intended Audience :: Developers
Classifier: License :: OSI Approved :: Zope Public License
Classifier: License :: OSI Approved :: GNU Library or Lesser General Public License (LGPL)
Classifier: Programming Language :: Python
Classifier: Programming Language :: Python :: 3
Classifier: Programming Language :: Python :: 3.9
Classifier: Programming Language :: Python :: 3.10
Classifier: Programming Language :: Python :: 3.11
Classifier: Programming Language :: Python :: 3.12
Classifier: Programming Language :: Python :: 3.13
Classifier: Topic :: Software Development :: Libraries :: Python Modules
Requires-Python: >=3.9
License-File: LICENSE.txt
Requires-Dist: setuptools
Requires-Dist: z3c.form>=3.2.10
Requires-Dist: zope.interface
Requires-Dist: zope.schema
Requires-Dist: zope.component
Requires-Dist: zope.i18nmessageid
Provides-Extra: test
Requires-Dist: lxml; extra == "test"
Requires-Dist: z3c.form[test]; extra == "test"
Requires-Dist: zope.testing; extra == "test"
Requires-Dist: zope.testrunner>=6.4; extra == "test"
Dynamic: author
Dynamic: author-email
Dynamic: classifier
Dynamic: description
Dynamic: home-page
Dynamic: keywords
Dynamic: license
Dynamic: provides-extra
Dynamic: requires-dist
Dynamic: requires-python
Dynamic: summary
